measureia/Sim_info.py
measureia/__init__.py
measureia/measure_IA.py
measureia/measure_IA_base.py
measureia/measure_jackknife.py
measureia/measure_m_box.py
measureia/measure_m_box_jk.py
measureia/measure_m_lightcone.py
measureia/measure_w_box.py
measureia/measure_w_box_jk.py
measureia/measure_w_lightcone.py
measureia/read_data.py
measureia/write_data.py
measureia-0.3.0.dist-info/WHEEL
measureia-0.3.0.dist-info/METADATA
measureia-0.3.0.dist-info/RECORD
