Metadata-Version: 2.3
Name: measureia
Version: 0.3.0
Summary: Measureing tool for intrinsic alignment correlation functions.
Author: Marloes van Heukelum
Author-email: Marloes van Heukelum <m.l.vanheukelum@uu.nl>
Requires-Dist: astropy~=6.1.0
Requires-Dist: h5py~=3.10.0
Requires-Dist: kmeans-radec
Requires-Dist: matplotlib~=3.10.6
Requires-Dist: numpy~=1.26.2
Requires-Dist: pathos~=0.3.1
Requires-Dist: pyccl~=3.2
Requires-Dist: scipy~=1.11.4
Requires-Dist: sympy~=1.12
Requires-Python: >=3.10
